MANIFEST.in
requirements.txt
setup.cfg
setup.py
napalm_base/__init__.py
napalm_base/base.py
napalm_base/constants.py
napalm_base/exceptions.py
napalm_base/helpers.py
napalm_base/mock.py
napalm_base/validate.py
napalm_base.egg-info/PKG-INFO
napalm_base.egg-info/SOURCES.txt
napalm_base.egg-info/dependency_links.txt
napalm_base.egg-info/entry_points.txt
napalm_base.egg-info/requires.txt
napalm_base.egg-info/top_level.txt
napalm_base/clitools/__init__.py
napalm_base/clitools/cl_napalm_configure.py
napalm_base/clitools/cl_napalm_test.py
napalm_base/clitools/cl_napalm_validate.py
napalm_base/clitools/helpers.py
napalm_base/test/__init__.py
napalm_base/test/base.py
napalm_base/test/conftest.py
napalm_base/test/double.py
napalm_base/test/getters.py
napalm_base/test/helpers.py
napalm_base/test/models.py
napalm_base/utils/__init__.py
napalm_base/utils/jinja_filters.py
napalm_base/utils/py23_compat.py
napalm_base/utils/string_parsers.py
test/__init__.py