Metadata-Version: 1.1
Name: napalm-base
Version: 0.24.2
Summary: Network Automation and Programmability Abstraction Layer with Multivendor support
Home-page: https://github.com/napalm-automation/napalm-base
Author: David Barroso, Kirk Byers, Mircea Ulinic
Author-email: dbarrosop@dravetech.com, ping@mirceaulinic.net, ktbyers@twb-tech.com
License: UNKNOWN
Platform: UNKNOWN
Classifier: Topic :: Utilities
Classifier: Programming Language :: Python
Classifier: Programming Language :: Python :: 2
Classifier: Programming Language :: Python :: 2.7
Classifier: Programming Language :: Python :: 3
Classifier: Programming Language :: Python :: 3.4
Classifier: Operating System :: POSIX :: Linux
Classifier: Operating System :: POSIX :: Linux
Classifier: Operating System :: MacOS
